agraffe/__init__.py
agraffe/types.py
agraffe/utils.py
agraffe/services/__init__.py
agraffe/services/aws_lambda.py
agraffe/services/azure_functions.py
agraffe/services/base.py
agraffe/services/google_cloud_functions.py
agraffe-0.7.0.dist-info/LICENSE
agraffe-0.7.0.dist-info/WHEEL
agraffe-0.7.0.dist-info/METADATA
agraffe-0.7.0.dist-info/RECORD
