Metadata-Version: 2.1
Name: agraffe
Version: 0.7.0
Summary: Agraffe, build API with ASGI in Serverless services (e.g AWS lambda, Google Cloud Functions and Azure Functions). 
Author-email: odd <odd12258053@gmail.com>
Requires-Python: >=3.7
Classifier: Intended Audience :: Information Technology
Classifier: Intended Audience :: System Administrators
Classifier: Operating System :: OS Independent
Classifier: Programming Language :: Python :: 3
Classifier: Programming Language :: Python
Classifier: Topic :: Software Development :: Libraries :: Application Frameworks
Classifier: Topic :: Software Development :: Libraries :: Python Modules
Classifier: Topic :: Software Development :: Libraries
Classifier: Topic :: Software Development
Classifier: Intended Audience :: Developers
Classifier: Programming Language :: Python :: 3 :: Only
Classifier: Programming Language :: Python :: 3.7
Classifier: Programming Language :: Python :: 3.8
Classifier: License :: OSI Approved :: MIT License
Requires-Dist: typing-extensions >=4.0.0, <5.0.0
Requires-Dist: mypy ==0.931 ; extra == "dev"
Requires-Dist: flake8 >=4.0.1, <5.0.0 ; extra == "dev"
Requires-Dist: black ==22.3.0 ; extra == "dev"
Requires-Dist: isort >=5.10.1, <6.0.0 ; extra == "dev"
Requires-Dist: azure-functions >=1.5.0, <2.0 ; extra == "dev"
Requires-Dist: pytest >=7.2.1, <8.0.0 ; extra == "test"
Requires-Dist: mypy ==0.931 ; extra == "test"
Requires-Dist: flake8 >=4.0.1, <5.0.0 ; extra == "test"
Requires-Dist: black ==22.3.0 ; extra == "test"
Requires-Dist: isort >=5.10.1, <6.0.0 ; extra == "test"
Requires-Dist: azure-functions >=1.5.0, <2.0 ; extra == "test"
Requires-Dist: functions-framework ==3.0.0 ; extra == "test"
Requires-Dist: fastapi >=0.94.0 ; extra == "test"
Requires-Dist: pydantic >=1.10.4 ; extra == "test"
Requires-Dist: python-multipart >=0.0.5 ; extra == "test"
Project-URL: Home, https://github.com/odd12258053/agraffe
Provides-Extra: dev
Provides-Extra: doc
Provides-Extra: test
